syntac_sdk/Syntac_Depth.py
syntac_sdk/Syntac_Shear.py
syntac_sdk/__init__.py
syntac_sdk/__pycache__/__init__.cpython-39.pyc
syntac_sdk/pyarmor_runtime_000000/__init__.py
syntac_sdk/pyarmor_runtime_000000/pyarmor_runtime.so
syntac_sdk/pyarmor_runtime_000000/__pycache__/__init__.cpython-39.pyc
syntac_sdk/tactile_ssl/__init__.py
syntac_sdk/tactile_ssl/algorithm/__init__.py
syntac_sdk/tactile_ssl/algorithm/dino.py
syntac_sdk/tactile_ssl/algorithm/module.py
syntac_sdk/tactile_ssl/data/vision_based_interactive.py
syntac_sdk/tactile_ssl/data/vision_tactile.py
syntac_sdk/tactile_ssl/data/vision_tactile_forcefield.py
syntac_sdk/tactile_ssl/data/digit/utils.py
syntac_sdk/tactile_ssl/downstream_task/__init__.py
syntac_sdk/tactile_ssl/downstream_task/attentive_pooler.py
syntac_sdk/tactile_ssl/downstream_task/forcefield_sl.py
syntac_sdk/tactile_ssl/downstream_task/sl_module.py
syntac_sdk/tactile_ssl/downstream_task/utils_forcefield/ssl_flow_loss.py
syntac_sdk/tactile_ssl/downstream_task/utils_forcefield/ssl_utils.py
syntac_sdk/tactile_ssl/downstream_task/utils_forcefield/layers/Fusion.py
syntac_sdk/tactile_ssl/downstream_task/utils_forcefield/layers/Head.py
syntac_sdk/tactile_ssl/downstream_task/utils_forcefield/layers/Reassemble.py
syntac_sdk/tactile_ssl/downstream_task/utils_forcefield/pose_estimator/PoseEstimator.py
syntac_sdk/tactile_ssl/downstream_task/utils_forcefield/pose_estimator/pose_decoder.py
syntac_sdk/tactile_ssl/downstream_task/utils_forcefield/pose_estimator/resnet_encoder.py
syntac_sdk/tactile_ssl/downstream_task/utils_forcefield/pose_estimator/utils.py
syntac_sdk/tactile_ssl/loss/dino_loss.py
syntac_sdk/tactile_ssl/loss/ibot_patch_loss.py
syntac_sdk/tactile_ssl/loss/koleo_loss.py
syntac_sdk/tactile_ssl/model/__init__.py
syntac_sdk/tactile_ssl/model/custom_scheduler.py
syntac_sdk/tactile_ssl/model/multimodal_transformer.py
syntac_sdk/tactile_ssl/model/pretrained.py
syntac_sdk/tactile_ssl/model/vision_transformer.py
syn_sdk-0.1.4.dist-info/METADATA
syn_sdk-0.1.4.dist-info/WHEEL
syn_sdk-0.1.4.dist-info/top_level.txt
syn_sdk-0.1.4.dist-info/RECORD
