Metadata-Version: 2.4
Name: syn_sdk
Version: 0.1.4
Summary: syntac_realese_env
Author: lvsj
Author-email: lvsj@sinxbot.com
Classifier: Programming Language :: Python :: 3
Requires-Python: >=3.10,<3.11
Requires-Dist: pillow>=10.0.0
Requires-Dist: numpy>=1.26.4
Requires-Dist: opencv-python>=4.9.0.80
Requires-Dist: scipy>=1.13.1
Requires-Dist: torch>=2.1.2
Requires-Dist: torchvision>=0.16.2
Requires-Dist: matplotlib>=3.9.1
Requires-Dist: ffmpeg-python
Requires-Dist: pyudev==0.24.4
Requires-Dist: lightning>=2.0.9.post0
Requires-Dist: xformers>=0.0.21
Requires-Dist: scikit-learn>=1.6.1
Requires-Dist: triton>=2.1.0
Requires-Dist: pyserial
Requires-Dist: omegaconf
Requires-Dist: einops
Requires-Dist: pyarmor==8.*
Requires-Dist: rich
Dynamic: author
Dynamic: author-email
Dynamic: classifier
Dynamic: requires-dist
Dynamic: requires-python
Dynamic: summary
